[
 {
   "occupant": "GONI Madeleine Epse WADEFAI",
   "identifier": "559302-H",
   "codept": "9-002-1PPGT",
   "pt": "Payeur Général",
   "prequired": "1;38",
   "crequired": "25;69",
   "preel": "1",
   "creel": "7;25;69",
   "activity": "100;101;102;103;104;105;106;107;108;109",
   "task": "",
   "date": "",
   "off": ""
 },
 {
   "occupant": "TAGOUNG TCHINDA Richard",
   "identifier": "670169-N",
   "codept": "9-002-1PSEC1",
   "pt": "Secrétariat PGT",
   "prequired": "24",
   "crequired": "28",
   "preel": "34",
   "creel": "10; 26;73",
   "activity": "",
   "task": "1;2;3;4;5;6;7",
   "date": "",
   "off": ""
 },
 {
   "occupant": "MEZILI MENDOUGA Alice Josèphe",
   "identifier": "671939-J",
   "codept": "9-002-1PSEC2",
   "pt": "Secrétariat PGT",
   "prequired": "24",
   "crequired": "28",
   "preel": "34",
   "creel": "10;73",
   "activity": "",
   "task": "1;2;3;4;5;6;7",
   "date": "",
   "off": ""
 },
 {
   "occupant": "ESSIANE André Patrice",
   "identifier": "656042-P",
   "codept": "9-002-1PCH1",
   "pt": "Chauffeur 1",
   "prequired": "58",
   "crequired": "11;20",
   "preel": "29",
   "creel": "11;73",
   "activity": "",
   "task": "105;106;107",
   "date": "",
   "off": ""
 },
 {
   "occupant": "ABAKAKA  MASSAO",
   "identifier": "E-096981",
   "codept": "9-002-1PCH2",
   "pt": "Chauffeur 2",
   "prequired": "58",
   "crequired": "11;20",
   "preel": "27",
   "creel": "11;73",
   "activity": "",
   "task": "105;106;107",
   "date": "",
   "off": ""
 },
 {
   "occupant": "NSI MVE Francine Aurélie Epse EDOU",
   "identifier": "636541-K",
   "codept": "9-002-2PFP1",
   "pt": "Fondé de Pouvoirs n°1",
   "prequired": "1;3;37;38",
   "crequired": "71; 72",
   "preel": "3",
   "creel": "7;13;25",
   "activity": "200;201;202;204;203;205;206;207;208;209;211;210;212",
   "task": "",
   "date": "",
   "off": ""
 },
 {
   "occupant": "ESSOLA MFOULA Salomé Marcelle",
   "identifier": "656043-X",
   "codept": "9-002-2PSEC3",
   "pt": "Secrétaire 1",
   "prequired": "24",
   "crequired": "28",
   "preel": "29",
   "creel": "10;28;73",
   "activity": "",
   "task": "1;2;3;4;5;6;7",
   "date": "",
   "off": ""
 },
 {
   "occupant": "BAKOA née NOA BIKIE Henriette Yollande",
   "identifier": "673554-J",
   "codept": "9-002-2PSEC4",
   "pt": "Secrétaire 2",
   "prequired": "24",
   "crequired": "28",
   "preel": "27",
   "creel": "10;28;73",
   "activity": "",
   "task": "1;2;3;4;5;6;7",
   "date": "",
   "off": ""
 },
 {
   "occupant": "EWOUNGOUO MANGA Martin",
   "identifier": "561753-J",
   "codept": "9-002-3PFP1",
   "pt": "Fondé de Pouvoirs n°2",
   "prequired": "1;3;37;38",
   "crequired": "71; 72;25",
   "preel": "1",
   "creel": "7;13;25;69",
   "activity": "300;301;302;303;304;305;306",
   "task": "",
   "date": "",
   "off": ""
 },
 {
   "occupant": "NGUEGANG TALONTSI Ervis",
   "identifier": "670127-A",
   "codept": "9-002-3PSEC5",
   "pt": "Secrétaire 1",
   "prequired": "24",
   "crequired": "28",
   "preel": "32",
   "creel": "10;26;73",
   "activity": "",
   "task": "1;2;3;4;5;6;7",
   "date": "",
   "off": ""
 },
 {
   "occupant": "MOUSTAPHA GARGA",
   "identifier": "586652-M",
   "codept": "9-002-4PCBV",
   "pt": "Chef de Brigade",
   "prequired": "1;3;37;38",
   "crequired": "71; 72;25",
   "preel": "1",
   "creel": "7;25;70",
   "activity": "400;401;402;403;404;405",
   "task": "",
   "date": "",
   "off": ""
 },
 {
   "occupant": "FAYCAL ABDOULAYE née MBAKO Pamela NWANKEM",
   "identifier": "615728-J",
   "codept": "9-002-4PIV1",
   "pt": "Inspecteur vérificateur 1",
   "prequired": "1;3;37;38",
   "crequired": "71; 72;25",
   "preel": "3",
   "creel": "7;25;46",
   "activity": "406;407",
   "task": "",
   "date": "",
   "off": ""
 },
 {
   "occupant": "MEYOBEME Agnès Elwir",
   "identifier": "601033-M",
   "codept": "9-002-4PIV2",
   "pt": "Inspecteur vérificateur 2",
   "prequired": "1;3;37;39",
   "crequired": "71; 72;25",
   "preel": "3",
   "creel": "7;25;46",
   "activity": "406;407",
   "task": "",
   "date": "",
   "off": ""
 },
 {
   "occupant": "ATSOPZE TAYO Mireille Epse KENFACK",
   "identifier": "601056-L",
   "codept": "9-002-4PIV3",
   "pt": "Inspecteur vérificateur 3",
   "prequired": "1;3;37;40",
   "crequired": "71; 72;25",
   "preel": "3",
   "creel": "7;25;46",
   "activity": "406;407",
   "task": "",
   "date": "",
   "off": ""
 },
 {
   "occupant": "TCHAMOU née LELE FONGUE Nadège Valery",
   "identifier": "646881-J",
   "codept": "9-002-4PIV4",
   "pt": "Inspecteur vérificateur 4",
   "prequired": "1;3;37;41",
   "crequired": "71; 72;25",
   "preel": "3",
   "creel": "6;7;25;46",
   "activity": "406;407",
   "task": "",
   "date": "",
   "off": ""
 },
 {
   "occupant": "",
   "identifier": "",
   "codept": "9-002-4PIV5",
   "pt": "Inspecteur vérificateur 5",
   "prequired": "1;3;37;42",
   "crequired": "71; 72;25",
   "preel": "",
   "creel": "",
   "activity": "406;407",
   "task": "",
   "date": "",
   "off": ""
 },
 {
   "occupant": "NOAH Emile Armand Didier",
   "identifier": "586333-H",
   "codept": "9-002-4PHT1",
   "pt": "Huissier du Trésor 1",
   "prequired": "1;3;37;42;5;6;7;8;9;10;11;33;34;35;36;39;40",
   "crequired": "73;25",
   "preel": "10",
   "creel": "7;25;26",
   "activity": "408",
   "task": "8;9;10",
   "date": "",
   "off": ""
 },
 {
   "occupant": "CHASSEP Valériane Aurèle Epse FOKOUA",
   "identifier": "726551-M",
   "codept": "9-002-4PCA1",
   "pt": "Cadre1",
   "prequired": "",
   "crequired": "",
   "preel": "3",
   "creel": "7;25;",
   "activity": "",
   "task": "",
   "date": "",
   "off": ""
 },
 {
   "occupant": "ENANIGN Y'OUBILITEK Estelle Laure\nEpse BOOTO",
   "identifier": "649360-N",
   "codept": "9-002-5PCS1",
   "pt": "Chef de service des depenses de matériel",
   "prequired": "1;3;37;38",
   "crequired": "45;25",
   "preel": "3",
   "creel": "7;25",
   "activity": "500;501;502;503",
   "task": "17;18;19;20",
   "date": "",
   "off": ""
 },
 {
   "occupant": "ONGBABOULE OTAM Béatrice",
   "identifier": "739918-Q",
   "codept": "9-002-5PCB1",
   "pt": "Chef de bureau des Caisses d'Avance",
   "prequired": "6;10;39;40",
   "crequired": "73;25",
   "preel": "33",
   "creel": "73",
   "activity": "409",
   "task": "11",
   "date": "",
   "off": ""
 },
 {
   "occupant": "NYANI ESSOMO Carice Stéphanie épse MANDA",
   "identifier": "753885-Y",
   "codept": "9-002-5PCB2",
   "pt": "Chef de bureau des Frais de Déplacement",
   "prequired": "6;10;39;40",
   "crequired": "73;25",
   "preel": "10",
   "creel": "7;25;46",
   "activity": "409",
   "task": "12",
   "date": "",
   "off": ""
 },
 {
   "occupant": "OKALA TSIMI Jean Michel",
   "identifier": "738433-L",
   "codept": "9-002-5PCB3",
   "pt": "Chef de bureau des Locations Administratives",
   "prequired": "6;10;39;40",
   "crequired": "73;25;1",
   "preel": "6",
   "creel": "7;13;25;46",
   "activity": "409",
   "task": "13;14",
   "date": "",
   "off": ""
 },
 {
   "occupant": "ESSOUKA ENGBOM Line",
   "identifier": "758683-M",
   "codept": "9-002-5PCB4",
   "pt": "Chef de bureau des Marchés",
   "prequired": "6;10;39;40",
   "crequired": "73;25;1",
   "preel": "6",
   "creel": "6;7;25;",
   "activity": "409",
   "task": "15",
   "date": "",
   "off": ""
 },
 {
   "occupant": "NGO BELL Débora Odile Epse BUM NDJENG",
   "identifier": "738426-B",
   "codept": "9-002-5PCB5",
   "pt": "Chef de bureau des Autres Dépenses de Matériel",
   "prequired": "6;10;39;40",
   "crequired": "73;25;1",
   "preel": "6",
   "creel": "7;25;46",
   "activity": "409",
   "task": "16",
   "date": "",
   "off": ""
 },
 {
   "occupant": "SANAMA ANONG Nadia Epse MVOM",
   "identifier": "U-035801",
   "codept": "9-002-5PCA2",
   "pt": "Cadre 1",
   "prequired": "",
   "crequired": "",
   "preel": "10",
   "creel": "6;7;25",
   "activity": "409",
   "task": "",
   "date": "",
   "off": ""
 },
 {
   "occupant": "NGO BILLONG Solange NTAMACK épse ROCK AUDU",
   "identifier": "736154-J",
   "codept": "9-002-5PCA3",
   "pt": "Cadre 2",
   "prequired": "",
   "crequired": "",
   "preel": "15",
   "creel": "25;73",
   "activity": "409",
   "task": "",
   "date": "",
   "off": ""
 },
 {
   "occupant": "YOMB Epse KHON Bibiane",
   "identifier": "740118-M",
   "codept": "9-002-5PCA4",
   "pt": "Cadre 3",
   "prequired": "",
   "crequired": "",
   "preel": "34",
   "creel": "73",
   "activity": "409",
   "task": "",
   "date": "",
   "off": ""
 },
 {
   "occupant": "MVONDO née EBA'A Salomé Mireille",
   "identifier": "664888-I",
   "codept": "9-002-5PCA5",
   "pt": "Cadre 4",
   "prequired": "",
   "crequired": "",
   "preel": "32",
   "creel": "73",
   "activity": "409",
   "task": "",
   "date": "",
   "off": ""
 },
 {
   "occupant": "EDJIMBI ZE Suzanne",
   "identifier": "667444-K",
   "codept": "9-002-5PAB1",
   "pt": "Agent de bureau 1",
   "prequired": "",
   "crequired": "",
   "preel": "29",
   "creel": "73",
   "activity": "409",
   "task": "108;109;110;111",
   "date": "",
   "off": ""
 },
 {
   "occupant": "AMBASSA Thierry",
   "identifier": "690017-H",
   "codept": "9-002-5PAB2",
   "pt": "Agent de bureau  2",
   "prequired": "",
   "crequired": "",
   "preel": "27",
   "creel": "73",
   "activity": "",
   "task": "108;109;110;111",
   "date": "",
   "off": ""
 },
 {
   "occupant": "ASTA MOHAMADOU MASSA",
   "identifier": "ECR",
   "codept": "9-002-5PAB3",
   "pt": "Agent de bureau",
   "prequired": "",
   "crequired": "",
   "preel": "15",
   "creel": "25",
   "activity": "",
   "task": "108;109;110;111",
   "date": "",
   "off": ""
 },
 {
   "occupant": "BENGONO MEWOUTOU Moïse Hector",
   "identifier": "586239-Y",
   "codept": "9-002-6PCS2",
   "pt": "Chef de service de la Comptabilité et de la Caisse",
   "prequired": "1;3;37;38",
   "crequired": "45;25",
   "preel": "3",
   "creel": "7;25",
   "activity": "600;601;602;603;604",
   "task": "21;22;23;24;25;26;27",
   "date": "",
   "off": ""
 },
 {
   "occupant": "MEKA BEKONO Marie Thérèse",
   "identifier": "774617-J",
   "codept": "9-002-6PCB6",
   "pt": "Chef de bureau d'Appui et de Liaison",
   "prequired": "6;10;39;40",
   "crequired": "73;25;1",
   "preel": "6",
   "creel": "7;25",
   "activity": "",
   "task": "28;29;30",
   "date": "",
   "off": ""
 },
 {
   "occupant": "YAOUBA BELLO",
   "identifier": "Z-035847",
   "codept": "9-002-6PCB7",
   "pt": "Chef de bureau de la Comptabilité",
   "prequired": "6;10;39;40",
   "crequired": "73;25;7;8",
   "preel": "10",
   "creel": "7;25",
   "activity": "410;411",
   "task": "31;32;33",
   "date": "",
   "off": ""
 },
 {
   "occupant": "MAGUIABOU FOTSO Elvine Audrey Epse ZOA",
   "identifier": "747632-D",
   "codept": "9-002-6PCB8",
   "pt": "Chef de bureau de l'Etat de Concordance Bancaire",
   "prequired": "6;10;39;40",
   "crequired": "73;25;7;8",
   "preel": "6",
   "creel": "7;25",
   "activity": "412;413",
   "task": "34;35;36;37;38",
   "date": "",
   "off": ""
 },
 {
   "occupant": "ANOI NDANGA épouse NDI MEKA",
   "identifier": "M-011087",
   "codept": "9-002-6PCB9",
   "pt": "Chef de bureau des Opérations Diverses",
   "prequired": "6;10;39;40",
   "crequired": "73;25;7;8",
   "preel": "10",
   "creel": "7;25",
   "activity": "",
   "task": "39;40",
   "date": "",
   "off": ""
 },
 {
   "occupant": "SEKEL Marlyse Epse MBASSI",
   "identifier": "601084-W",
   "codept": "9-002-6PCB10",
   "pt": "Chef de bureau des Réglements par Virement",
   "prequired": "6;10;39;40",
   "crequired": "73;25;1",
   "preel": "6",
   "creel": "7;25",
   "activity": "414",
   "task": "41;42;43",
   "date": "",
   "off": ""
 },
 {
   "occupant": "TIMBEN Sylivis TEBIT Epse FONGWE",
   "identifier": "758996-V",
   "codept": "9-002-6PCB11",
   "pt": "Chef de bureau des règlements par Cheque Special du Tresor",
   "prequired": "6;10;39;40",
   "crequired": "73;25;1",
   "preel": "6",
   "creel": "7;25",
   "activity": "",
   "task": "44;45;46;47",
   "date": "",
   "off": ""
 },
 {
   "occupant": "MENGUE Chantal Ornella",
   "identifier": "758824-W",
   "codept": "9-002-6PCB12",
   "pt": "Chef de bureau de la Saisie",
   "prequired": "6;10;39;40",
   "crequired": "73;25;1",
   "preel": "6",
   "creel": "7;25",
   "activity": "415",
   "task": "",
   "date": "",
   "off": ""
 },
 {
   "occupant": "KIJEM née Chalesta NYWA Forchang",
   "identifier": "586350-M",
   "codept": "9-002-6PCP",
   "pt": "Caissière Principale",
   "prequired": "6;10;39;40",
   "crequired": "25",
   "preel": "6",
   "creel": "7;25",
   "activity": "",
   "task": "48;49;50;51;52;53",
   "date": "",
   "off": ""
 },
 {
   "occupant": "MOABOULOU BILE Marie Paule Epse ZOA",
   "identifier": "700495-J",
   "codept": "9-002-6PSC1",
   "pt": "Sous Caissière 1",
   "prequired": "41;25;26;27;28;29;30;31",
   "crequired": "73",
   "preel": "6",
   "creel": "7;25",
   "activity": "",
   "task": "54;55;56",
   "date": "",
   "off": ""
 },
 {
   "occupant": "MBWANG Myriam MPODE",
   "identifier": "780369-Y",
   "codept": "9-002-6PSC2",
   "pt": "Sous Caissière 2",
   "prequired": "41;25;26;27;28;29;30;31",
   "crequired": "73",
   "preel": "15",
   "creel": "7;25",
   "activity": "",
   "task": "54;55;56",
   "date": "",
   "off": ""
 },
 {
   "occupant": "BELLA NDJOUA Prudence",
   "identifier": "L-011205",
   "codept": "9-002-6PSC3",
   "pt": "Sous Caissière 3",
   "prequired": "41;25;26;27;28;29;30;31",
   "crequired": "73",
   "preel": "10",
   "creel": "7;25",
   "activity": "",
   "task": "54;55;56",
   "date": "",
   "off": ""
 },
 {
   "occupant": "BWANG MYRIAM MPODE",
   "identifier": "780369-Y",
   "codept": "9-002-6PCA6",
   "pt": "Cadre 1",
   "prequired": "6;10;39;40",
   "crequired": "73;25;7;8",
   "preel": "10",
   "creel": "7;25",
   "activity": "",
   "task": "39;40",
   "date": "",
   "off": ""
 },
 {
   "occupant": "AKOUMO ADJIBOLO Gisèle Nadège",
   "identifier": "B-002631",
   "codept": "9-002-6PCA7",
   "pt": "Cadre 2",
   "prequired": "",
   "crequired": "",
   "preel": "12",
   "creel": "73",
   "activity": "1322",
   "task": "",
   "date": "",
   "off": ""
 },
 {
   "occupant": "MBEZELE SEDENA Balbine Solange",
   "identifier": "740479-M",
   "codept": "9-002-6PCA8",
   "pt": "Cadre 3",
   "prequired": "",
   "crequired": "",
   "preel": "32",
   "creel": "73",
   "activity": "1322",
   "task": "",
   "date": "",
   "off": ""
 },
 {
   "occupant": "MBONI ENAMA Patrick",
   "identifier": "784907-S",
   "codept": "9-002-6PCA9",
   "pt": "Cadre 4",
   "prequired": "",
   "crequired": "",
   "preel": "32",
   "creel": "73",
   "activity": "1322",
   "task": "",
   "date": "",
   "off": ""
 },
 {
   "occupant": "LEFANG Celestina NKENG",
   "identifier": "586574-V",
   "codept": "9-002-7PCS3",
   "pt": "Chef de service des oppositions",
   "prequired": "1;3;37;38",
   "crequired": "45;25",
   "preel": "1",
   "creel": "7;25;60",
   "activity": "701;702;703;704",
   "task": "",
   "date": "",
   "off": ""
 },
 {
   "occupant": "NZUME Vivian MECHANG",
   "identifier": "670723-W",
   "codept": "9-002-7PCB13",
   "pt": "Chef de bureau de l'Exploitation et de la Relance",
   "prequired": "6;10;39;40",
   "crequired": "73;25",
   "preel": "34",
   "creel": "73",
   "activity": "",
   "task": "57;58",
   "date": "",
   "off": ""
 },
 {
   "occupant": "DJELLA née FOUDA Huguette",
   "identifier": "674363-M",
   "codept": "9-002-7PCB14",
   "pt": "Chef de bureau des Bulletins de Liquidation de Recettes",
   "prequired": "6;10;39;40",
   "crequired": "73;25",
   "preel": "34",
   "creel": "73",
   "activity": "1306",
   "task": "59",
   "date": "",
   "off": ""
 },
 {
   "occupant": "FAOUZIATOU HAMADOU Epse BOUKAR",
   "identifier": "785593-H",
   "codept": "9-002-7PCB15",
   "pt": "Chef de bureau des Retenues sur Dépenses de Matériel",
   "prequired": "6;10;39;40",
   "crequired": "73;25",
   "preel": "10",
   "creel": "7;25",
   "activity": "",
   "task": "60",
   "date": "",
   "off": ""
 },
 {
   "occupant": "AMOUGOU KYE Romaric Aubin",
   "identifier": "A-011171",
   "codept": "9-002-7PCB16",
   "pt": "Chef de bureau des Retenues sur Solde",
   "prequired": "6;10;39;40",
   "crequired": "73;25",
   "preel": "6",
   "creel": "7;25",
   "activity": "",
   "task": "61",
   "date": "",
   "off": ""
 },
 {
   "occupant": "YAMNJEM NCHOUTPOUEN FADIMATOU",
   "identifier": "740808-G",
   "codept": "9-002-7PCA10",
   "pt": "Cadre 1",
   "prequired": "",
   "crequired": "",
   "preel": "60",
   "creel": "73",
   "activity": "1322",
   "task": "",
   "date": "",
   "off": ""
 },
 {
   "occupant": "ESSEBE KOUMGANG Alvine Victoire",
   "identifier": "F-035642",
   "codept": "9-002-7PCA11",
   "pt": "Cadre 2",
   "prequired": "",
   "crequired": "",
   "preel": "3",
   "creel": "7;25",
   "activity": "1322",
   "task": "",
   "date": "",
   "off": ""
 },
 {
   "occupant": "MEMBA Bertrand FOKA",
   "identifier": "764363-J",
   "codept": "9-002-7PCA12",
   "pt": "Cadre 3",
   "prequired": "",
   "crequired": "",
   "preel": "15",
   "creel": "7;25",
   "activity": "1322",
   "task": "",
   "date": "",
   "off": ""
 },
 {
   "occupant": "MVEI MANI SOMBO AMBA",
   "identifier": "636525-A",
   "codept": "9-002-8PCS4",
   "pt": "Chef de service de la Solde et des Pensions",
   "prequired": "1;3;37;38",
   "crequired": "45;25",
   "preel": "3",
   "creel": "7;25;47",
   "activity": "800;801;802;803;804",
   "task": "",
   "date": "",
   "off": ""
 },
 {
   "occupant": "ZOUE ELA Nicole",
   "identifier": "667107-V",
   "codept": "9-002-8PCB17",
   "pt": "Chef de bureau de la Liaison Informatique",
   "prequired": "6;10;39;40",
   "crequired": "73;25",
   "preel": "34",
   "creel": "73",
   "activity": "",
   "task": "62;63;64",
   "date": "",
   "off": ""
 },
 {
   "occupant": "NGA ATEBA Nadine Epse MBIDA",
   "identifier": "738438-L",
   "codept": "9-002-8PCB18",
   "pt": "Chef de bureau des Personnels Civils et Fin",
   "prequired": "6;10;39;40;55",
   "crequired": "73;25;19",
   "preel": "10",
   "creel": "7;25",
   "activity": "",
   "task": "65;66;67",
   "date": "",
   "off": ""
 },
 {
   "occupant": "GERME Georgette Epse KOM",
   "identifier": "738455-E",
   "codept": "9-002-8PCB19",
   "pt": "Chef de bureau des Personnels Educatifs et Sociaux",
   "prequired": "6;10;39;40",
   "crequired": "73;25;1",
   "preel": "10",
   "creel": "7;25",
   "activity": "",
   "task": "68;69;70",
   "date": "",
   "off": ""
 },
 {
   "occupant": "ZAMBO Christophe Borgia",
   "identifier": "662182-H",
   "codept": "9-002-8PCB20",
   "pt": "Chef de bureau des Personnels Judiciaires et Techniques",
   "prequired": "6;10;39;40",
   "crequired": "73;25;13;14",
   "preel": "32",
   "creel": "73",
   "activity": "",
   "task": "71;72;73",
   "date": "",
   "off": ""
 },
 {
   "occupant": "EPWENE KENNETH Alobwede",
   "identifier": "675010-K",
   "codept": "9-002-8PCB21",
   "pt": "Chef de bureau des Pensions",
   "prequired": "6;10;39;40",
   "crequired": "73;25;1",
   "preel": "34",
   "creel": "73",
   "activity": "",
   "task": "74;75;76",
   "date": "",
   "off": ""
 },
 {
   "occupant": "NDOBEDE Constance Epole",
   "identifier": "675470-L",
   "codept": "9-002-8PCA13",
   "pt": "Cadre 1",
   "prequired": "",
   "crequired": "",
   "preel": "32",
   "creel": "73",
   "activity": "1322",
   "task": "",
   "date": "",
   "off": ""
 },
 {
   "occupant": "ELOUNDOU MBASSI Jean Jacques",
   "identifier": "785829-D",
   "codept": "9-002-8PCA14",
   "pt": "Cadre 2",
   "prequired": "",
   "crequired": "",
   "preel": "3",
   "creel": "7;25",
   "activity": "1322",
   "task": "",
   "date": "",
   "off": ""
 },
 {
   "occupant": "SAMBA AMASSA Louisette Marie\nEpse KINGUE",
   "identifier": "C-035798",
   "codept": "9-002-8PCA15",
   "pt": "Cadre 3",
   "prequired": "",
   "crequired": "",
   "preel": "3",
   "creel": "7;25",
   "activity": "1322",
   "task": "",
   "date": "",
   "off": ""
 },
 {
   "occupant": "ABOMO MENDO Nadine",
   "identifier": "655975-Z",
   "codept": "9-002-8PCA16",
   "pt": "Cadre 4",
   "prequired": "",
   "crequired": "",
   "preel": "27",
   "creel": "73",
   "activity": "1322",
   "task": "",
   "date": "",
   "off": ""
 },
 {
   "occupant": "KELEMBA NZEUSSEU Dorvale",
   "identifier": "700473-Z",
   "codept": "9-002-8PCA17",
   "pt": "Cadre 5",
   "prequired": "",
   "crequired": "",
   "preel": "10",
   "creel": "7;25",
   "activity": "1322",
   "task": "",
   "date": "",
   "off": ""
 },
 {
   "occupant": "AKOA EBO'O Georges Camille",
   "identifier": "584881-G",
   "codept": "9-002-9PCS5",
   "pt": "Chef de service des Titres de Reglement",
   "prequired": "1;3;37;38",
   "crequired": "45;25;1",
   "preel": "1",
   "creel": "7;25;60",
   "activity": "900;901;902;903;904",
   "task": "",
   "date": "",
   "off": ""
 },
 {
   "occupant": "DTCHETMI NOUBISSI Simone",
   "identifier": "589161-S",
   "codept": "9-002-9PCB22",
   "pt": "Chef de bureau de Rattachement",
   "prequired": "6;10;39;40",
   "crequired": "73;25",
   "preel": "6",
   "creel": "7;25;47",
   "activity": "",
   "task": "77;78;79",
   "date": "",
   "off": ""
 },
 {
   "occupant": "NGA EKANI Ives Roger",
   "identifier": "W-079872",
   "codept": "9-002-9PCB23",
   "pt": "Chef de bureau des Titres de Reglement",
   "prequired": "6;10;39;40",
   "crequired": "73;25",
   "preel": "32",
   "creel": "73",
   "activity": "1306;1307;1308;1309;1310;1311",
   "task": "80",
   "date": "",
   "off": ""
 },
 {
   "occupant": "AÏSSATOU BOUBA",
   "identifier": "732448-Y",
   "codept": "9-002-9PCB24",
   "pt": "Chef de bureau du Contentieux des Titres",
   "prequired": "6;10;39;40",
   "crequired": "73;25",
   "preel": "34",
   "creel": "73",
   "activity": "1322;1313;1314;1315;1316",
   "task": "81",
   "date": "",
   "off": ""
 },
 {
   "occupant": "ESSOMBA née BILO'O Nicole II",
   "identifier": "674769-E",
   "codept": "9-002-9PCA18",
   "pt": "Cadre 1",
   "prequired": "",
   "crequired": "",
   "preel": "34",
   "creel": "73",
   "activity": "1322",
   "task": "",
   "date": "",
   "off": ""
 },
 {
   "occupant": "GUIDEING GODWE Mariam",
   "identifier": "755157-R",
   "codept": "9-002-9PCA19",
   "pt": "Cadre 2",
   "prequired": "",
   "crequired": "",
   "preel": "34",
   "creel": "73",
   "activity": "1322",
   "task": "",
   "date": "",
   "off": ""
 },
 {
   "occupant": "ZINTSEM A NYAM Jean Jacques",
   "identifier": "776711-S",
   "codept": "9-002-9PCA20",
   "pt": "Cadre 3",
   "prequired": "",
   "crequired": "",
   "preel": "60",
   "creel": "73",
   "activity": "1322",
   "task": "",
   "date": "",
   "off": ""
 },
 {
   "occupant": "ATEBA MALLA NDJANA Jacqueline \nEpse EMAH",
   "identifier": "659762-A",
   "codept": "9-002-9PAB4",
   "pt": "Agent de bureau",
   "prequired": "",
   "crequired": "",
   "preel": "27",
   "creel": "73",
   "activity": "1322",
   "task": "",
   "date": "",
   "off": ""
 },
 {
   "occupant": "ABONG BOUNTSEBE Alvine Michelle",
   "identifier": "700316-B",
   "codept": "9-002-10PCS6",
   "pt": "Chef de service du Compte de Gestion",
   "prequired": "1;3;37;38",
   "crequired": "45;25",
   "preel": "3",
   "creel": "7;25",
   "activity": "1000;1001;1002;1003;1004;1005",
   "task": "",
   "date": "",
   "off": ""
 },
 {
   "occupant": "DANYANG DJORO Noêl",
   "identifier": "G-011239",
   "codept": "9-002-10PCB25",
   "pt": "Chef de bureau du Compte de Gestion",
   "prequired": "6;10;39;40",
   "crequired": "73;25",
   "preel": "10",
   "creel": "7;25",
   "activity": "1317;1318",
   "task": "82;83;84",
   "date": "",
   "off": ""
 },
 {
   "occupant": "MEKA Serge Claverie",
   "identifier": "752637-J",
   "codept": "9-002-10PCB26",
   "pt": "Chef de bureau des Archives",
   "prequired": "6;10;39;40",
   "crequired": "73;25",
   "preel": "32",
   "creel": "73",
   "activity": "",
   "task": "85;86",
   "date": "",
   "off": ""
 },
 {
   "occupant": "ABINA Paulin",
   "identifier": "ECR",
   "codept": "9-002-10PAB5",
   "pt": "Agent de bureau",
   "prequired": "",
   "crequired": "",
   "preel": "15",
   "creel": "25",
   "activity": "",
   "task": "108;109;110;111",
   "date": "",
   "off": ""
 },
 {
   "occupant": "MBARGA Laurent Arsène",
   "identifier": "ECR",
   "codept": "9-002-10PAB6",
   "pt": "Agent de bureau",
   "prequired": "",
   "crequired": "",
   "preel": "15",
   "creel": "25",
   "activity": "",
   "task": "108;109;110;111",
   "date": "",
   "off": ""
 },
 {
   "occupant": "MANDZE Gorati NGANFUFU",
   "identifier": "ECR",
   "codept": "9-002-10PAB7",
   "pt": "Agent de bureau",
   "prequired": "",
   "crequired": "",
   "preel": "15",
   "creel": "25",
   "activity": "",
   "task": "108;109;110;111",
   "date": "",
   "off": ""
 },
 {
   "occupant": "NGAMGA ENGAL Kevin Aimé",
   "identifier": "ECR",
   "codept": "9-002-10PAB8",
   "pt": "Agent de bureau",
   "prequired": "",
   "crequired": "",
   "preel": "19",
   "creel": "25",
   "activity": "",
   "task": "108;109;110;111",
   "date": "",
   "off": ""
 },
 {
   "occupant": "NHIOMOG KODNA Samuel Brice",
   "identifier": "ECR",
   "codept": "9-002-10PAB9",
   "pt": "Agent de bureau",
   "prequired": "",
   "crequired": "",
   "preel": "19",
   "creel": "25",
   "activity": "",
   "task": "108;109;110;111",
   "date": "",
   "off": ""
 },
 {
   "occupant": "DIBOUNDJE BOGOLIONG Charles",
   "identifier": "ECR",
   "codept": "9-002-10PAB10",
   "pt": "Agent de bureau",
   "prequired": "",
   "crequired": "",
   "preel": "19",
   "creel": "25",
   "activity": "",
   "task": "108;109;110;111",
   "date": "",
   "off": ""
 },
 {
   "occupant": "ABBA AMSSAMI",
   "identifier": "689014-P",
   "codept": "9-002-11PCS7",
   "pt": "Chef SCTIC",
   "prequired": "1;3;37;38",
   "crequired": "45;25",
   "preel": "1",
   "creel": "7;25;60",
   "activity": "1100;1101",
   "task": "",
   "date": "",
   "off": ""
 },
 {
   "occupant": "NDEMBA Jules Franck Junior",
   "identifier": "737325-J",
   "codept": "9-002-11PCB27",
   "pt": "Chef de bureau de la Reception des Comptabilités",
   "prequired": "6;10;39;40",
   "crequired": "73;25",
   "preel": "10",
   "creel": "7;25",
   "activity": "",
   "task": "87;88;89",
   "date": "",
   "off": ""
 },
 {
   "occupant": "NGONO ONDOA René Bertrand",
   "identifier": "700469-Y",
   "codept": "9-002-11PCB28",
   "pt": "Chef de bureau de Contrôle Formel et de Validation",
   "prequired": "6;10;39;40",
   "crequired": "73;25",
   "preel": "10",
   "creel": "7;25",
   "activity": "",
   "task": "90",
   "date": "",
   "off": ""
 },
 {
   "occupant": "NOAH OLIBOKO Martin",
   "identifier": "674886-Y",
   "codept": "9-002-11PCB29",
   "pt": "Chef de bureau du Traitement Informatique des Comptabilités",
   "prequired": "6;10;39;40",
   "crequired": "73;25",
   "preel": "32",
   "creel": "73",
   "activity": "",
   "task": "91;92",
   "date": "",
   "off": ""
 },
 {
   "occupant": "DANKAM TCHAPTCHET OUKOUATOU Laetitia Epse NEOSSI",
   "identifier": "X-011236",
   "codept": "9-002-11PCB30",
   "pt": "Chef de bureau des Rejets Comptables",
   "prequired": "6;10;39;40",
   "crequired": "73;25",
   "preel": "10",
   "creel": "25",
   "activity": "",
   "task": "93;94;95",
   "date": "",
   "off": ""
 },
 {
   "occupant": "OBIYIHA Rachel Taylor Micheline Epse KAMAL",
   "identifier": "646905-K",
   "codept": "9-002-11PCA21",
   "pt": "Cadre 1",
   "prequired": "",
   "crequired": "",
   "preel": "3",
   "creel": "73",
   "activity": "1322",
   "task": "",
   "date": "",
   "off": ""
 },
 {
   "occupant": "FOLLUH ANOUYASHINEU Elvis",
   "identifier": "646885-A",
   "codept": "9-002-12PCS8",
   "pt": "Chef de service des Déposants",
   "prequired": "1;3;37;38",
   "crequired": "45;25",
   "preel": "3",
   "creel": "7;25",
   "activity": "1200;1201;1203;1204;1205",
   "task": "",
   "date": "",
   "off": ""
 },
 {
   "occupant": "AWONO MBATAMA Leah Aline",
   "identifier": "646921-U",
   "codept": "9-002-12PCB31",
   "pt": "Chef de bureau des Operations des EPA",
   "prequired": "6;10;39;40",
   "crequired": "73;25",
   "preel": "10",
   "creel": "7;25",
   "activity": "1319",
   "task": "",
   "date": "",
   "off": ""
 },
 {
   "occupant": "ABENA BEDIGA Camille Liboire",
   "identifier": "688779-J",
   "codept": "9-002-12PCB32",
   "pt": "Chef de bureau des Operations des Autres Correspondants",
   "prequired": "6;10;39;40",
   "crequired": "73;25",
   "preel": "10",
   "creel": "7;25",
   "activity": "",
   "task": "96",
   "date": "",
   "off": ""
 },
 {
   "occupant": "MANGA Renne Emmanuelle",
   "identifier": "747937-Q",
   "codept": "9-002-12PCA22",
   "pt": "Cadre 1",
   "prequired": "",
   "crequired": "",
   "preel": "34",
   "creel": "73",
   "activity": "1322",
   "task": "",
   "date": "",
   "off": ""
 },
 {
   "occupant": "MBALA Chantal Martine",
   "identifier": "667491-H",
   "codept": "9-002-12PAB11",
   "pt": "Agent de bureau",
   "prequired": "",
   "crequired": "",
   "preel": "29",
   "creel": "73",
   "activity": "",
   "task": "",
   "date": "",
   "off": ""
 },
 {
   "occupant": "SOBZE née NDAGOE TEGOMO Clarisse",
   "identifier": "589127-Q",
   "codept": "9-002-13PCS9",
   "pt": "Chef de service du Portefeuille",
   "prequired": "1;3;37;38",
   "crequired": "45;25",
   "preel": "3",
   "creel": "7;25",
   "activity": "1300;1301;1302;1303;1304",
   "task": "97;98;99;100;101",
   "date": "",
   "off": ""
 },
 {
   "occupant": "FATIMA ABAKAR",
   "identifier": "737483-P",
   "codept": "9-002-13PCB33",
   "pt": "Chef de bureau du Portefeuille",
   "prequired": "6;10;39;40",
   "crequired": "73;25",
   "preel": "3",
   "creel": "7;25",
   "activity": "1320",
   "task": "102;103",
   "date": "",
   "off": ""
 },
 {
   "occupant": "TAFON MAGDALENE TITUK Epse TEBOH",
   "identifier": "A-011088",
   "codept": "9-002-13PCB34",
   "pt": "Chef de bureau des Précomptes",
   "prequired": "6;10;39;40",
   "crequired": "73;25",
   "preel": "10",
   "creel": "7;25",
   "activity": "",
   "task": "104",
   "date": "",
   "off": ""
 },
 {
   "occupant": "KOLOKO Sariette",
   "identifier": "758750-H",
   "codept": "9-002-13PCB35",
   "pt": "Chef de bureau des Opérations Spécifiques",
   "prequired": "6;10;39;40",
   "crequired": "73;25",
   "preel": "10",
   "creel": "7;25",
   "activity": "1321",
   "task": "",
   "date": "",
   "off": ""
 },
 {
   "occupant": "FENE BELLO Rodrigue Herbert",
   "identifier": "E-011306",
   "codept": "9-002-13PCB36",
   "pt": "Chef de bureau",
   "prequired": "",
   "crequired": "",
   "preel": "6",
   "creel": "7;25",
   "activity": "1322",
   "task": "",
   "date": "",
   "off": ""
 }
]